smoloki/__init__.py
smoloki/__main__.py
smoloki-0.1.2.dist-info/METADATA
smoloki-0.1.2.dist-info/WHEEL
smoloki-0.1.2.dist-info/entry_points.txt
smoloki-0.1.2.dist-info/top_level.txt
smoloki-0.1.2.dist-info/RECORD
