Metadata-Version: 2.4
Name: smoloki
Version: 0.1.2
Summary: Tiny library to push logs to `Grafana Loki` in `logfmt` format.
Home-page: https://github.com/michaelkryukov/smoloki
Author: Michael Krukov
Author-email: krukov.michael@ya.ru
Keywords: library,loki
Classifier: Programming Language :: Python :: 3
Classifier: Programming Language :: Python :: 3 :: Only
Classifier: License :: OSI Approved :: MIT License
Classifier: Operating System :: OS Independent
Classifier: Intended Audience :: Developers
Requires-Python: >=3.7
Requires-Dist: aiohttp<4,>=3.8.3
Dynamic: author
Dynamic: author-email
Dynamic: classifier
Dynamic: description
Dynamic: description-content-type
Dynamic: home-page
Dynamic: keywords
Dynamic: requires-dist
Dynamic: requires-python
Dynamic: summary
